metabase_query/__init__.py
metabase_query/card.py
metabase_query/dataset.py
metabase_query/sql.py
metabase_query/utils.py
metabase_query-1.0.9.dist-info/licenses/LICENSE
metabase_query-1.0.9.dist-info/METADATA
metabase_query-1.0.9.dist-info/WHEEL
metabase_query-1.0.9.dist-info/top_level.txt
metabase_query-1.0.9.dist-info/RECORD
