Metadata-Version: 2.4
Name: metabase-query
Version: 1.0.9
Summary: Metabase query API with any URL and easy to filter.
Home-page: https://github.com/tranngocminhhieu/metabase-query
Author: Tran Ngoc Minh Hieu
Author-email: tnmhieu@gmail.com
License-File: LICENSE
Requires-Dist: tenacity
Requires-Dist: nest-asyncio
Requires-Dist: aiohttp
Requires-Dist: asyncio
Dynamic: author
Dynamic: author-email
Dynamic: description
Dynamic: description-content-type
Dynamic: home-page
Dynamic: license-file
Dynamic: requires-dist
Dynamic: summary
